{
    "classes": [
        "Carlos Sainz Jr.",
        "Charles Leclerc",
        "George Russell",
        "Lando Norris",
        "Lewis Hamilton",
        "Max Verstappen",
        "Oscar Piastri"
    ],
    "intercepts": [
        -0.5509710434376502,
        -0.12979848816266076,
        -0.12979848816264697,
        -0.8267105603488426,
        2.463989140460632,
        -0.8267105603488425
    ],
    "coefficients": [
        [
            2.88498671189026,
            -0.16787479346024572
        ],
        [
            -0.4054198757435685,
            -0.227326581318539
        ],
        [
            -0.40541987574356847,
            -0.2273265813185389
        ],
        [
            -0.23162812633711907,
            -0.126066398417079
        ],
        [
            -1.6108907077288857,
            0.8746607529314816
        ],
        [
            -0.23162812633711913,
            -0.12606639841707903
        ]
    ],
    "winner_classes": {
        "0": "Carlos Sainz Jr.",
        "1": "Charles Leclerc",
        "2": "George Russell",
        "3": "Lando Norris",
        "4": "Lewis Hamilton",
        "5": "Max Verstappen",
        "6": "Oscar Piastri"
    },
    "feature_order": [
        "race_name_Austrian Grand Prix",
        "race_name_Bahrain Grand Prix",
        "race_name_British Grand Prix",
        "race_name_Canadian Grand Prix",
        "race_name_Dutch Grand Prix",
        "race_name_Emilia Romagna Grand Prix",
        "race_name_Hungarian Grand Prix",
        "race_name_Japanese Grand Prix",
        "race_name_Las Vegas Grand Prix",
        "race_name_Miami Grand Prix",
        "race_name_Monaco Grand Prix",
        "race_name_Qatar Grand Prix",
        "race_name_Saudi Arabian Grand Prix",
        "race_name_Spanish Grand Prix",
        "race_name_S\u00e3o Paulo Grand Prix",
        "race_name_United States Grand Prix",
        "circuit_Bahrain International Circuit",
        "circuit_Circuit Gilles Villeneuve",
        "circuit_Circuit Zandvoort",
        "circuit_Circuit de Barcelona\u2013Catalunya",
        "circuit_Circuit de Monaco",
        "circuit_Circuit of the Americas",
        "circuit_Hungaroring",
        "circuit_Imola Circuit",
        "circuit_Interlagos",
        "circuit_Jeddah Corniche Circuit",
        "circuit_Las Vegas Street Circuit",
        "circuit_Lusail International Circuit",
        "circuit_Miami International Autodrome",
        "circuit_Red Bull Ring",
        "circuit_Silverstone Circuit",
        "circuit_Suzuka Circuit",
        "winner_car_name_RB20",
        "winner_car_name_SF-24",
        "winner_car_name_W15",
        "weather_encoded",
        "winner_constructor_points",
        "winner_constructor_wins",
        "winner_constructor_podiums",
        "winner_car_wins",
        "winner_car_podiums",
        "cluster_1",
        "cluster_2"
    ],
    "weather_encoding": {
        "f": 0,
        "t": 1
    },
    "best_params": {
        "logreg__C": 10,
        "logreg__solver": "lbfgs",
        "scaler": "StandardScaler()"
    }
}